FastTelethonhelper/FastTelethon.py
FastTelethonhelper/__init__.py
FastTelethonhelper-1.0.7.dist-info/LICENSE
FastTelethonhelper-1.0.7.dist-info/METADATA
FastTelethonhelper-1.0.7.dist-info/WHEEL
FastTelethonhelper-1.0.7.dist-info/top_level.txt
FastTelethonhelper-1.0.7.dist-info/RECORD
