Metadata-Version: 2.1
Name: FastTelethonhelper
Version: 1.0.7
Summary: Make Telethon files upload/download faster
Home-page: https://github.com/MiyukiKun/FastTelethonhelper
Author: MiyukiKun
Author-email: hardikmajethia9529@gmail.com
Classifier: Programming Language :: Python :: 3.6
Classifier: Programming Language :: Python :: 3.7
Classifier: Programming Language :: Python :: 3.8
Classifier: Programming Language :: Python :: 3.9
Classifier: Operating System :: OS Independent
License-File: LICENSE
